whalrus/__init__.py
whalrus/cli.py
whalrus/whalrus.py
whalrus/ballots/__init__.py
whalrus/ballots/ballot.py
whalrus/ballots/ballot_levels.py
whalrus/ballots/ballot_one_name.py
whalrus/ballots/ballot_order.py
whalrus/ballots/ballot_plurality.py
whalrus/ballots/ballot_veto.py
whalrus/converters_ballot/converter_ballot.py
whalrus/converters_ballot/converter_ballot_general.py
whalrus/converters_ballot/converter_ballot_to_grades.py
whalrus/converters_ballot/converter_ballot_to_levels.py
whalrus/converters_ballot/converter_ballot_to_levels_interval.py
whalrus/converters_ballot/converter_ballot_to_levels_list_non_numeric.py
whalrus/converters_ballot/converter_ballot_to_levels_list_numeric.py
whalrus/converters_ballot/converter_ballot_to_levels_range.py
whalrus/converters_ballot/converter_ballot_to_order.py
whalrus/converters_ballot/converter_ballot_to_plurality.py
whalrus/converters_ballot/converter_ballot_to_strict_order.py
whalrus/converters_ballot/converter_ballot_to_veto.py
whalrus/eliminations/__init__.py
whalrus/eliminations/elimination.py
whalrus/eliminations/elimination_below_average.py
whalrus/eliminations/elimination_last.py
whalrus/matrices/matrix.py
whalrus/matrices/matrix_majority.py
whalrus/matrices/matrix_ranked_pairs.py
whalrus/matrices/matrix_schulze.py
whalrus/matrices/matrix_weighted_majority.py
whalrus/priorities/priority.py
whalrus/profiles/__init__.py
whalrus/profiles/profile.py
whalrus/rules/__init__.py
whalrus/rules/rule.py
whalrus/rules/rule_approval.py
whalrus/rules/rule_baldwin.py
whalrus/rules/rule_black.py
whalrus/rules/rule_borda.py
whalrus/rules/rule_bucklin_by_rounds.py
whalrus/rules/rule_bucklin_instant.py
whalrus/rules/rule_condorcet.py
whalrus/rules/rule_coombs.py
whalrus/rules/rule_copeland.py
whalrus/rules/rule_irv.py
whalrus/rules/rule_iterated_elimination.py
whalrus/rules/rule_k_approval.py
whalrus/rules/rule_kim_roush.py
whalrus/rules/rule_majority_judgment.py
whalrus/rules/rule_maximin.py
whalrus/rules/rule_nanson.py
whalrus-0.4.6.dist-info/AUTHORS.rst
whalrus-0.4.6.dist-info/LICENSE
whalrus-0.4.6.dist-info/METADATA
whalrus-0.4.6.dist-info/WHEEL
whalrus-0.4.6.dist-info/entry_points.txt
whalrus-0.4.6.dist-info/top_level.txt
whalrus-0.4.6.dist-info/RECORD
