Metadata-Version: 2.1
Name: whalrus
Version: 0.4.6
Summary: Which Alternative Represents Us, a package for voting rules
Home-page: https://github.com/francois-durand/whalrus
Author: François Durand
Author-email: fradurand@gmail.com
License: GNU General Public License v3
Keywords: whalrus
Platform: UNKNOWN
Classifier: Development Status :: 2 - Pre-Alpha
Classifier: Intended Audience :: Developers
Classifier: License :: OSI Approved :: GNU General Public License v3 (GPLv3)
Classifier: Natural Language :: English
Classifier: Programming Language :: Python :: 3
Classifier: Programming Language :: Python :: 3.6
Classifier: Programming Language :: Python :: 3.7
Classifier: Programming Language :: Python :: 3.8
Requires-Dist: Click (>=6.0)
Requires-Dist: numpy
Requires-Dist: toolz
Requires-Dist: pyparsing
